wagtail_translate/__init__.py
wagtail_translate/apps.py
wagtail_translate/fields.py
wagtail_translate/monkeypatch_model.py
wagtail_translate/monkeypatch_page.py
wagtail_translate/signals.py
wagtail_translate/default_behaviour/__init__.py
wagtail_translate/default_behaviour/apps.py
wagtail_translate/default_behaviour/signals.py
wagtail_translate/translators/__init__.py
wagtail_translate/translators/base.py
wagtail_translate/translators/deepl.py
wagtail_translate/translators/rot13.py
wagtail_translate-0.3.0.dist-info/LICENSE
wagtail_translate-0.3.0.dist-info/WHEEL
wagtail_translate-0.3.0.dist-info/METADATA
wagtail_translate-0.3.0.dist-info/RECORD
